README.md
setup.cfg
setup.py
Flask_Electron.egg-info/PKG-INFO
Flask_Electron.egg-info/SOURCES.txt
Flask_Electron.egg-info/dependency_links.txt
Flask_Electron.egg-info/not-zip-safe
Flask_Electron.egg-info/requires.txt
Flask_Electron.egg-info/top_level.txt
flask_electron/__init__.py
flask_electron/logger.py
flask_electron/auth/__init__.py
flask_electron/auth/decorators.py
flask_electron/auth/jwt.py
flask_electron/blueprint/__init__.py
flask_electron/blueprint/core.py
flask_electron/blueprint/endpoints.py
flask_electron/common/__init__.py
flask_electron/common/exceptions.py
flask_electron/dao/__init__.py
flask_electron/dao/actions.py
flask_electron/dao/base.py
flask_electron/dao/data.py
flask_electron/dao/query.py
flask_electron/http/__init__.py
flask_electron/http/exceptions.py
flask_electron/http/responses.py
flask_electron/sqlalchemy/__init__.py
flask_electron/sqlalchemy/declarative.py
flask_electron/sqlalchemy/serializer.py
flask_electron/sqlalchemy/models/__init__.py
flask_electron/sqlalchemy/models/user/__init__.py
flask_electron/sqlalchemy/models/user/dao.py
flask_electron/sqlalchemy/models/user/user.py
tests/__init__.py
tests/db/__init__.py
tests/db/flaskalchemy/__init__.py
tests/db/flaskalchemy/test_serializer.py