Metadata-Version: 2.1
Name: Flask-Electron
Version: 0.4.9
Summary: Core code for Flask based projects
Home-page: https://github.com/kmjbyrne/flask-electron
Author: Keith Byrne
Author-email: keithmbyrne@gmail.com
License: MIT
Keywords: python library utilities
Platform: UNKNOWN
Classifier: Development Status :: 3 - Alpha
Classifier: License :: OSI Approved :: MIT License
Classifier: Programming Language :: Python :: 3.7
